{"generated_at":"2026-06-23","node_count":1306,"edge_count":8597,"community_count":16,"top_hubs":[{"id":"wiki/overview/humanoid-paper-notebooks-index.md","label":"Humanoid Paper Notebooks 知识库索引","degree":430},{"id":"wiki/overview/paper-notebook-category-04-loco-manipulation-and-wbc.md","label":"Paper Notebooks · Loco-Manipulation and WBC","degree":261},{"id":"wiki/concepts/sim2real.md","label":"Sim2Real","degree":215},{"id":"wiki/tasks/locomotion.md","label":"Locomotion","degree":209},{"id":"wiki/overview/humanoid-rl-motion-control-body-system-stack.md","label":"人形机器人 RL 运动控制：身体系统栈视角","degree":182},{"id":"wiki/methods/reinforcement-learning.md","label":"Reinforcement Learning (RL, 强化学习)","degree":174},{"id":"wiki/methods/vla.md","label":"VLA（Vision-Language-Action）","degree":166},{"id":"wiki/overview/paper-notebook-category-05-locomotion.md","label":"Paper Notebooks · Locomotion","degree":153},{"id":"wiki/tasks/manipulation.md","label":"Manipulation","degree":145},{"id":"wiki/methods/imitation-learning.md","label":"Imitation Learning (IL, 模仿学习)","degree":140}],"orphan_nodes":[],"type_distribution":{"entity":876,"method":108,"overview":97,"concept":85,"query":55,"formalization":38,"comparison":33,"task":12,"reference":1,"roadmap_page":1},"community_distribution":{"人形论文深读笔记（Humanoid Paper Notebooks） 社区":209,"视觉-语言-动作（VLA） 社区":197,"运动控制（Locomotion） 社区":167,"其他社区":149,"全身控制（Whole-Body Control, WBC） 社区":102,"模仿学习（Imitation Learning, IL） 社区":101,"人形 RL 运动控制（Humanoid RL Locomotion） 社区":85,"仿真训练（Isaac Gym / Isaac Lab） 社区":53,"操作（Manipulation） 社区":51,"行为基础模型技术地图（BFM） 社区":48,"人形硬件技术地图（Humanoid Hardware 101） 社区":36,"论文深读 · 人体动作（Human Motion） 社区":33,"接触丰富型操作（Contact-Rich Manipulation） 社区":24,"机器人操作系统 2 基础（ROS 2） 社区":24,"强化学习（Reinforcement Learning, RL） 社区":20,"仿真到现实（Sim2Real） 社区":7},"community_quality":{"singleton_communities":[],"largest_community_ratio":0.16,"community_quality_warning":false},"latest_wiki_nodes":[{"path":"wiki/entities/numerical-optimization-curriculum.md","detail_id":"entity-numerical-optimization-curriculum","label":"数值优化学习策展（机器人 L0+）","type":"entity","recency":"2026-06-23","source":"log.md"},{"path":"wiki/formalizations/convex-functions.md","detail_id":"wiki-formalizations-convex-functions","label":"Convex Functions（凸函数）","type":"formalization","recency":"2026-06-23","source":"log.md"},{"path":"wiki/formalizations/kkt-conditions.md","detail_id":"wiki-formalizations-kkt-conditions","label":"KKT Conditions（KKT 条件）","type":"formalization","recency":"2026-06-23","source":"log.md"},{"path":"wiki/formalizations/quadratic-programming.md","detail_id":"wiki-formalizations-quadratic-programming","label":"Quadratic Programming（二次规划）","type":"formalization","recency":"2026-06-23","source":"log.md"},{"path":"wiki/formalizations/symmetric-cone-programming.md","detail_id":"wiki-formalizations-symmetric-cone-programming","label":"Symmetric Cone Programming（对称锥规划）","type":"formalization","recency":"2026-06-23","source":"log.md"},{"path":"wiki/formalizations/adjoint-sensitivity-analysis.md","detail_id":"wiki-formalizations-adjoint-sensitivity-analysis","label":"Adjoint Sensitivity Analysis（伴随灵敏度分析）","type":"formalization","recency":"2026-06-23","source":"log.md"},{"path":"wiki/methods/line-search-steepest-descent.md","detail_id":"wiki-methods-line-search-steepest-descent","label":"Line Search & Steepest Descent（线搜索与最速下降）","type":"method","recency":"2026-06-23","source":"log.md"},{"path":"wiki/methods/quasi-newton-bfgs.md","detail_id":"wiki-methods-quasi-newton-bfgs","label":"Quasi-Newton BFGS / L-BFGS（拟牛顿法）","type":"method","recency":"2026-06-23","source":"log.md"},{"path":"wiki/methods/conjugate-gradient-method.md","detail_id":"wiki-methods-conjugate-gradient-method","label":"Conjugate Gradient Method（共轭梯度法）","type":"method","recency":"2026-06-23","source":"log.md"},{"path":"wiki/methods/penalty-barrier-augmented-lagrangian.md","detail_id":"wiki-methods-penalty-barrier-augmented-lagrangian","label":"Penalty / Barrier / Augmented Lagrangian（罚函数、障碍法与增广拉格朗日）","type":"method","recency":"2026-06-23","source":"log.md"},{"path":"wiki/methods/nonlinear-model-predictive-control.md","detail_id":"wiki-methods-nonlinear-model-predictive-control","label":"Nonlinear Model Predictive Control（NMPC）","type":"method","recency":"2026-06-23","source":"log.md"},{"path":"wiki/methods/time-optimal-path-parameterization.md","detail_id":"wiki-methods-time-optimal-path-parameterization","label":"Time-Optimal Path Parameterization（TOPP）","type":"method","recency":"2026-06-23","source":"log.md"},{"path":"wiki/methods/smooth-navigation-path-generation.md","detail_id":"wiki-methods-smooth-navigation-path-generation","label":"Smooth Navigation Path Generation（平滑导航路径生成）","type":"method","recency":"2026-06-23","source":"log.md"},{"path":"wiki/methods/convex-relaxation-robotics.md","detail_id":"wiki-methods-convex-relaxation-robotics","label":"Convex Relaxation in Robotics（机器人凸松弛）","type":"method","recency":"2026-06-23","source":"log.md"},{"path":"wiki/concepts/constrained-optimization.md","detail_id":"wiki-concepts-constrained-optimization","label":"Constrained Optimization（约束优化）","type":"concept","recency":"2026-06-23","source":"log.md"},{"path":"wiki/concepts/control-allocation.md","detail_id":"wiki-concepts-control-allocation","label":"Control Allocation（控制分配）","type":"concept","recency":"2026-06-23","source":"log.md"},{"path":"wiki/concepts/collision-distance-optimization.md","detail_id":"wiki-concepts-collision-distance-optimization","label":"Collision Distance Optimization（碰撞距离优化）","type":"concept","recency":"2026-06-23","source":"log.md"},{"path":"wiki/queries/optimization-software-selection.md","detail_id":"wiki-queries-optimization-software-selection","label":"Optimization Software Selection（优化软件选型）","type":"query","recency":"2026-06-23","source":"log.md"},{"path":"wiki/concepts/optimal-control.md","detail_id":"wiki-concepts-optimal-control","label":"Optimal Control (OCP)","type":"concept","recency":"2026-06-23","source":"log.md"},{"path":"wiki/methods/trajectory-optimization.md","detail_id":"wiki-methods-trajectory-optimization","label":"Trajectory Optimization（轨迹优化）","type":"method","recency":"2026-06-23","source":"log.md"}],"latest_wiki_node":{"path":"wiki/entities/numerical-optimization-curriculum.md","detail_id":"entity-numerical-optimization-curriculum","label":"数值优化学习策展（机器人 L0+）","type":"entity","recency":"2026-06-23","source":"log.md"}}