{
  "generated_at": "2026-06-19",
  "node_count": 1257,
  "edge_count": 8186,
  "coverage": {
    "covered": 1227,
    "total": 1255,
    "percent": 98
  },
  "latest_wiki_nodes": [
    {
      "path": "wiki/entities/metahuman.md",
      "detail_id": "entity-metahuman",
      "label": "MetaHuman（Epic 数字人平台）",
      "type": "entity",
      "recency": "2026-06-19",
      "source": "log.md"
    },
    {
      "path": "wiki/concepts/motion-retargeting.md",
      "detail_id": "wiki-concepts-motion-retargeting",
      "label": "Motion Retargeting（动作重定向）",
      "type": "concept",
      "recency": "2026-06-19",
      "source": "log.md"
    },
    {
      "path": "wiki/entities/mixamo.md",
      "detail_id": "entity-mixamo",
      "label": "Mixamo",
      "type": "entity",
      "recency": "2026-06-19",
      "source": "log.md"
    },
    {
      "path": "wiki/entities/blender.md",
      "detail_id": "entity-blender",
      "label": "Blender（开源 3D 创作套件）",
      "type": "entity",
      "recency": "2026-06-19",
      "source": "log.md"
    },
    {
      "path": "wiki/methods/crisp-real2sim.md",
      "detail_id": "wiki-methods-crisp-real2sim",
      "label": "CRISP（Contact-guided Real2Sim）",
      "type": "method",
      "recency": "2026-06-19",
      "source": "log.md"
    },
    {
      "path": "wiki/entities/paper-mujica-wheel-legged-multi-skill.md",
      "detail_id": "entity-paper-mujica-wheel-legged-multi-skill",
      "label": "MUJICA：轮足多技能统一本体控制架构",
      "type": "entity",
      "recency": "2026-06-19",
      "source": "log.md"
    },
    {
      "path": "wiki/concepts/wheel-legged-quadruped.md",
      "detail_id": "wiki-concepts-wheel-legged-quadruped",
      "label": "轮足四足机器人（四轮足 / Wheel-Legged Quadruped）",
      "type": "concept",
      "recency": "2026-06-19",
      "source": "log.md"
    },
    {
      "path": "wiki/tasks/hybrid-locomotion.md",
      "detail_id": "wiki-tasks-hybrid-locomotion",
      "label": "Hybrid Locomotion (混合运动)",
      "type": "task",
      "recency": "2026-06-19",
      "source": "log.md"
    },
    {
      "path": "wiki/tasks/locomotion.md",
      "detail_id": "wiki-tasks-locomotion",
      "label": "Locomotion",
      "type": "task",
      "recency": "2026-06-19",
      "source": "log.md"
    },
    {
      "path": "wiki/concepts/sim2real.md",
      "detail_id": "wiki-concepts-sim2real",
      "label": "Sim2Real",
      "type": "concept",
      "recency": "2026-06-19",
      "source": "log.md"
    },
    {
      "path": "wiki/entities/paper-swap-parkour.md",
      "detail_id": "entity-paper-swap-parkour",
      "label": "SWAP：对称等变世界模型四足跑酷",
      "type": "entity",
      "recency": "2026-06-19",
      "source": "log.md"
    },
    {
      "path": "wiki/tasks/stair-obstacle-perceptive-locomotion.md",
      "detail_id": "wiki-tasks-stair-obstacle-perceptive-locomotion",
      "label": "楼梯与障碍 Locomotion（感知 / 盲走中心节点）",
      "type": "task",
      "recency": "2026-06-19",
      "source": "log.md"
    },
    {
      "path": "wiki/entities/extreme-parkour.md",
      "detail_id": "entity-extreme-parkour",
      "label": "Extreme Parkour（端到端四足感知跑酷）",
      "type": "entity",
      "recency": "2026-06-19",
      "source": "log.md"
    },
    {
      "path": "wiki/entities/paper-phygile.md",
      "detail_id": "entity-paper-phygile",
      "label": "PhyGile（Physics-Prefix Guided Motion Generation for Agile General Humanoid Motion Tracking）",
      "type": "entity",
      "recency": "2026-06-19",
      "source": "log.md"
    },
    {
      "path": "wiki/methods/diffusion-motion-generation.md",
      "detail_id": "wiki-methods-diffusion-motion-generation",
      "label": "Diffusion-based Motion Generation (基于扩散模型的运动生成)",
      "type": "method",
      "recency": "2026-06-19",
      "source": "log.md"
    },
    {
      "path": "wiki/queries/humanoid-motion-tracking-method-selection.md",
      "detail_id": "wiki-queries-humanoid-motion-tracking-method-selection",
      "label": "人形运动跟踪方法选型指南",
      "type": "query",
      "recency": "2026-06-19",
      "source": "log.md"
    },
    {
      "path": "wiki/entities/paper-notebook-gmt.md",
      "detail_id": "entity-paper-notebook-gmt",
      "label": "GMT",
      "type": "entity",
      "recency": "2026-06-19",
      "source": "log.md"
    },
    {
      "path": "wiki/entities/paper-humanoid-gpt.md",
      "detail_id": "entity-paper-humanoid-gpt",
      "label": "Humanoid-GPT（Scaling Data and Structure for Zero-Shot Motion Tracking）",
      "type": "entity",
      "recency": "2026-06-19",
      "source": "log.md"
    },
    {
      "path": "wiki/methods/mtrg-reference-goal-driven-rl.md",
      "detail_id": "wiki-methods-mtrg-reference-goal-driven-rl",
      "label": "MTRG / GfR: Multi-Task Reference and Goal-Driven RL",
      "type": "method",
      "recency": "2026-06-19",
      "source": "log.md"
    },
    {
      "path": "wiki/comparisons/hil-vs-mtrg-vs-zest-parkour-imitation.md",
      "detail_id": "wiki-comparisons-hil-vs-mtrg-vs-zest-parkour-imitation",
      "label": "HIL vs MTRG vs ZEST：跑酷模仿学习路线对比",
      "type": "comparison",
      "recency": "2026-06-19",
      "source": "log.md"
    }
  ],
  "latest_wiki_node": {
    "path": "wiki/entities/metahuman.md",
    "detail_id": "entity-metahuman",
    "label": "MetaHuman（Epic 数字人平台）",
    "type": "entity",
    "recency": "2026-06-19",
    "source": "log.md"
  }
}