{
  "generated_at": "2026-05-20",
  "node_count": 394,
  "edge_count": 2778,
  "coverage": {
    "covered": 392,
    "total": 392,
    "percent": 100
  },
  "latest_wiki_nodes": [
    {
      "path": "wiki/entities/amp-mjlab.md",
      "detail_id": "entity-amp-mjlab",
      "label": "AMP_mjlab (G1 统一 AMP 策略)",
      "type": "entity",
      "recency": "2026-05-20",
      "source": "log.md"
    }
  ],
  "latest_wiki_node": {
    "path": "wiki/entities/amp-mjlab.md",
    "detail_id": "entity-amp-mjlab",
    "label": "AMP_mjlab (G1 统一 AMP 策略)",
    "type": "entity",
    "recency": "2026-05-20",
    "source": "log.md"
  }
}