{
  "PPO 样本效率": {
    "terms": [
      "PPO"
    ],
    "pos_claims": [
      "PPO.*样本效率.*高|高.*样本效率.*PPO|PPO.*sample.efficient"
    ],
    "neg_claims": [
      "PPO.*样本效率.*低|PPO.*sample.inefficient|PPO.*样本效率差"
    ]
  },
  "MPC 实时性": {
    "terms": [
      "MPC",
      "model.predictive"
    ],
    "pos_claims": [
      "MPC.*实时|实时.*MPC|MPC.*real.?time|MPC.*online"
    ],
    "neg_claims": [
      "MPC.*无法实时|MPC.*not real.?time|MPC.*计算量.*过大.*实时"
    ]
  },
  "Domain Randomization 必要性": {
    "terms": [
      "domain.randomization",
      "域随机"
    ],
    "pos_claims": [
      "必须|必要|sim2real.*必|是.*sim2real.*关键"
    ],
    "neg_claims": [
      "降低.*in.distribution|DR.*不.*必要|不需要.*domain.*random|domain.*random.*unnecessary"
    ]
  },
  "RL 推理速度": {
    "terms": [
      "policy",
      "RL",
      "强化学习"
    ],
    "pos_claims": [
      "推理.*快|推理延迟.*低|inference.*fast|low.*latency"
    ],
    "neg_claims": [
      "推理.*慢|推理.*延迟.*高|inference.*slow|latency.*high"
    ]
  },
  "WBC 计算复杂度": {
    "terms": [
      "WBC",
      "whole.body"
    ],
    "pos_claims": [
      "实时|real.?time|efficient|高效|fast"
    ],
    "neg_claims": [
      "WBC.*计算量大|WBC.*computationally expensive|WBC.*not real.?time|WBC.*无法实时"
    ]
  },
  "接触力估计精度": {
    "terms": [
      "contact",
      "接触力"
    ],
    "pos_claims": [
      "精确.*估计|accurate.*estimation|高精度"
    ],
    "neg_claims": [
      "估计不准|inaccurate|sim2real.*gap.*contact|接触.*仿真.*差距"
    ]
  },
  "TSID 基于 QP": {
    "terms": [
      "TSID"
    ],
    "pos_claims": [
      "基于.*QP|QP.*框架|QP.*求解|二次规划.*求解"
    ],
    "neg_claims": [
      "不.*基于.*QP|独立.*于.*QP|非.*QP.*方法|TSID.*不.*基于"
    ]
  },
  "WBC 多接触优势": {
    "terms": [
      "WBC",
      "whole.body"
    ],
    "pos_claims": [
      "优于|多接触.*优|必要|必须.*控制|统一.*优化"
    ],
    "neg_claims": [
      "WBC.*完全没用|WBC.*没有.*多接触优势|WBC.*没必要.*多接触"
    ]
  },
  "MuJoCo 接触精度": {
    "terms": [
      "mujoco",
      "MuJoCo"
    ],
    "pos_claims": [
      "精确|accurate|高精度|精度.*高|接触.*真实"
    ],
    "neg_claims": [
      "不精确|不适合.*接触|接触.*gap.*大|contact.*inaccurate"
    ]
  },
  "仿真频率对接触稳定性": {
    "terms": [
      "仿真频率|simulation.*frequenc|sim.*freq"
    ],
    "pos_claims": [
      "关键|重要|必须|稳定.*必要|stability.*critical|高频.*稳定"
    ],
    "neg_claims": [
      "频率.*无关|低频.*足够|频率.*不重要|不影响.*稳定"
    ]
  },
  "GAE λ 范围": {
    "terms": [
      "GAE",
      "广义优势"
    ],
    "pos_claims": [
      "λ.*\\(0.*1\\)|lambda.*0.*1|λ.*介于|0.*<.*λ.*<.*1"
    ],
    "neg_claims": [
      "λ.*>.*1|λ.*<.*0|GAE.*无.*λ|GAE.*不.*用.*lambda"
    ]
  },
  "EKF 线性化误差": {
    "terms": [
      "EKF",
      "Extended Kalman"
    ],
    "pos_claims": [
      "线性化|lineariz|一阶近似|first.order"
    ],
    "neg_claims": [
      "EKF.*精确非线性|EKF.*无线性化误差|EKF.*exact"
    ]
  },
  "Model-Based RL 样本效率": {
    "terms": [
      "model.based.*rl|model.based.*reinforcement|基于模型.*强化"
    ],
    "pos_claims": [
      "样本效率.*高|sample.*efficient|数据效率.*高|更.*efficient"
    ],
    "neg_claims": [
      "model.based.*样本效率.*低|model.based.*inefficient|数据效率.*差"
    ]
  },
  "Diffusion Policy 推理延迟": {
    "terms": [
      "diffusion.policy",
      "扩散策略"
    ],
    "pos_claims": [
      "去噪.*步数|denoising.*step|推理.*多步|multi.*step.*inference"
    ],
    "neg_claims": [
      "diffusion.*单步|diffusion.*instant|扩散.*无延迟|denoising.*free"
    ]
  },
  "WBC 优先级约束": {
    "terms": [
      "WBC",
      "whole.body"
    ],
    "pos_claims": [
      "优先级|priority|层次|hierarchy|安全.*约束.*首"
    ],
    "neg_claims": [
      "WBC.*无优先级|WBC.*等权|WBC.*flat.*weight"
    ]
  },
  "Sim2Real 主流手段": {
    "terms": [
      "sim2real",
      "sim.to.real"
    ],
    "pos_claims": [
      "domain.*randomization|域随机|DR.*|adaptive.*domain"
    ],
    "neg_claims": [
      "sim2real.*无需随机|sim2real.*only.*real.*data"
    ]
  },
  "Retargeting 运动学约束": {
    "terms": [
      "retarget",
      "重定向"
    ],
    "pos_claims": [
      "运动学.*约束|kinematic.*constraint|关节.*限制.*重定向|需要.*匹配.*运动学"
    ],
    "neg_claims": [
      "重定向.*仅.*角度|retarget.*just.*angle|retarget.*no.*constraint"
    ]
  },
  "PPO Clip 范围": {
    "terms": [
      "PPO",
      "clip"
    ],
    "pos_claims": [
      "clip.*ratio|ε.*=.*0\\.[12]|epsilon.*clip|裁剪.*比率"
    ],
    "neg_claims": [
      "PPO.*无.*clip|PPO.*不.*裁剪|clip.*unnecessary"
    ]
  },
  "接触互补性条件": {
    "terms": [
      "complementarity|互补性|接触.*互补"
    ],
    "pos_claims": [
      "φ.*≥.*0|λ.*≥.*0|非负|non.negative|互补.*约束"
    ],
    "neg_claims": [
      "接触.*无约束|contact.*unconstrained|互补.*不必要"
    ]
  },
  "DAgger 数据效率": {
    "terms": [
      "DAgger"
    ],
    "pos_claims": [
      "比.*BC.*数据效率.*高|解决.*分布漂移|处理.*covariate shift|缓解.*covariate shift"
    ],
    "neg_claims": [
      "与.*BC.*等价|不处理.*covariate shift|不处理.*分布漂移"
    ]
  },
  "VLA 推理延迟": {
    "terms": [
      "VLA|Vision.Language.Action|RT-2|π₀|pi0"
    ],
    "pos_claims": [
      "50ms\\+|50ms以上|推理延迟.*高|控制频率.*低|latency.*50"
    ],
    "neg_claims": [
      "实时性.*传统控制器相当|与.*传统控制器相当|低延迟.*1kHz|高频闭环.*无需缓冲"
    ]
  },
  "行为克隆 compounding error": {
    "terms": [
      "Behavior Cloning|行为克隆|\bBC\b"
    ],
    "pos_claims": [
      "compounding error|错误累积|累积误差|covariate shift"
    ],
    "neg_claims": [
      "累积误差.*无关|序列长度.*无关|不会.*错误累积"
    ]
  },
  "接触力摩擦约束": {
    "terms": [
      "接触|contact|摩擦锥|friction cone"
    ],
    "pos_claims": [
      "\\|f_\\{?xy\\}?\\|.*<=.*(μ|mu).*f_z|\\|f_t\\|.*<=.*mu.*f_n|摩擦锥.*约束|friction cone"
    ],
    "neg_claims": [
      "无需.*摩擦锥|不需要.*摩擦锥|contact force.*unconstrained"
    ]
  },
  "腿足地形感知": {
    "terms": [
      "地形|terrain|腿足|locomotion|高度图|point cloud"
    ],
    "pos_claims": [
      "高度图|点云|height map|point cloud|地形感知"
    ],
    "neg_claims": [
      "不需要.*地形感知|无需.*高度图|无需.*点云"
    ]
  },
  "MiniLM 向量维度": {
    "terms": [
      "MiniLM|all-MiniLM-L6-v2"
    ],
    "pos_claims": [
      "384.*维|384-dim|384维"
    ],
    "neg_claims": [
      "768.*维|768-dim|768维"
    ]
  },
  "Marp 幻灯片格式": {
    "terms": [
      "Marp"
    ],
    "pos_claims": [
      "Markdown.*frontmatter|frontmatter.*Markdown|生成.*幻灯片"
    ],
    "neg_claims": [
      "需要.*LaTeX|需要.*Beamer|必须.*LaTeX"
    ]
  },
  "sentence-transformers CPU": {
    "terms": [
      "sentence-transformers|SentenceTransformer"
    ],
    "pos_claims": [
      "CPU.*运行|可在.*CPU.*运行|无需.*GPU|without GPU"
    ],
    "neg_claims": [
      "必须.*GPU|only.*GPU|cannot.*CPU"
    ]
  },
  "VLA 训练数据规模": {
    "terms": [
      "VLA|RT-1|RT-2|π₀|pi0"
    ],
    "pos_claims": [
      "大量.*演示|数千\\+|130k\\+|大规模.*数据|多样化.*演示"
    ],
    "neg_claims": [
      "十条.*演示|10条.*演示|少量.*演示.*收敛"
    ]
  },
  "BM25 参数含义": {
    "terms": [
      "BM25|k1|\bb\b"
    ],
    "pos_claims": [
      "k1.*词频.*饱和|b.*长度归一化|长度归一化.*b|词频饱和.*k1"
    ],
    "neg_claims": [
      "b.*与词频无关|b.*控制词频|k1.*长度归一化"
    ]
  },
  "π₀ Flow Matching": {
    "terms": [
      "π₀|pi0|Flow Matching|flow matching"
    ],
    "pos_claims": [
      "Flow Matching|flow matching|连续动作.*生成"
    ],
    "neg_claims": [
      "不.*用.*Flow Matching|仅.*Transformer.*直接回归|without.*flow matching"
    ]
  },
  "CBF 安全集条件": {
    "terms": [
      "CBF|Control Barrier Function|控制障碍函数"
    ],
    "pos_claims": [
      "h\\(x\\).*≥.*0|安全集.*h.*≥|维持.*安全集|超平面.*h.*≥.*0"
    ],
    "neg_claims": [
      "CBF.*直接优化.*性能|CBF.*最大化.*奖励|CBF.*优化.*目标函数"
    ]
  },
  "CLF 指数衰减条件": {
    "terms": [
      "CLF|Control Lyapunov Function|控制李雅普诺夫"
    ],
    "pos_claims": [
      "V̇.*≤.*-.*α.*V|衰减.*条件|指数.*衰减|dot.*V.*≤.*-.*alpha"
    ],
    "neg_claims": [
      "CLF.*无需.*衰减|Lyapunov.*无衰减条件|CLF.*不要求.*导数.*负"
    ]
  },
  "双臂闭链约束": {
    "terms": [
      "双臂|bimanual|dual.arm"
    ],
    "pos_claims": [
      "闭链|closed.loop.*kinematic|closed-loop.*kinematic|闭环运动学|闭链约束"
    ],
    "neg_claims": [
      "双臂.*独立.*单臂|bimanual.*two.*independent|双臂.*各自独立"
    ]
  },
  "Anki TSV 字段分隔符": {
    "terms": [
      "Anki|anki",
      "TSV|tsv"
    ],
    "pos_claims": [
      "制表符|Tab.*分隔|tab.separated|\\t.*分隔符"
    ],
    "neg_claims": [
      "逗号.*分隔|comma.*separated|CSV.*Anki|Anki.*CSV"
    ]
  },
  "WBC QP 求解时间": {
    "terms": [
      "WBC|whole.body",
      "QP|二次规划"
    ],
    "pos_claims": [
      "50.*200.*μs|OSQP.*微秒|QP.*求解.*50|QP.*μs"
    ],
    "neg_claims": [
      "WBC.*QP.*秒级|WBC.*求解.*几秒|QP.*second.*WBC"
    ]
  },
  "特权训练非对称 Actor": {
    "terms": [
      "特权训练|privileged.*training|teacher.student|asymmetric.*actor"
    ],
    "pos_claims": [
      "非对称|asymmetric.*actor|Teacher.*有.*特权|Student.*无.*特权|训练时.*额外"
    ],
    "neg_claims": [
      "特权训练.*对称|teacher.*student.*相同.*观测|privileged.*symmetric"
    ]
  },
  "Foundation Policy 预训练数据规模": {
    "terms": [
      "foundation.*policy|基础策略模型|RT-1|Octo"
    ],
    "pos_claims": [
      "130k\\+|大规模.*演示|多机器人.*形态|800k|跨.*任务.*预训练"
    ],
    "neg_claims": [
      "RT-1.*少量.*数据|foundation.*policy.*百条|基础策略.*低数据"
    ]
  },
  "模仿学习分布外泛化": {
    "terms": [
      "imitation.*learning|模仿学习|behavior.*cloning|行为克隆"
    ],
    "pos_claims": [
      "分布外.*失败|out.*of.*distribution|分布偏移|covariate shift|compounding"
    ],
    "neg_claims": [
      "模仿学习.*分布外.*稳定|BC.*不受.*分布偏移.*影响|IL.*robust.*distribution"
    ]
  },
  "HQP 优先级层次": {
    "terms": [
      "HQP|Hierarchical.*QP|层次化.*QP"
    ],
    "pos_claims": [
      "优先级|priority|层次|hierarchy|高优先级.*先满足"
    ],
    "neg_claims": [
      "HQP.*无优先级|HQP.*等权.*优化|hierarchical.*no.*priority"
    ]
  },
  "PPO on-policy 特性": {
    "terms": [
      "PPO"
    ],
    "pos_claims": [
      "PPO.*on.policy|PPO.*每次.*更新.*丢弃|PPO.*不.*复用.*历史数据"
    ],
    "neg_claims": [
      "PPO 是 off.policy|PPO 属于 off.policy|PPO 本质上.*off.policy|PPO.*replay buffer.*来.*复用"
    ]
  },
  "Contact-rich 接触力建模": {
    "terms": [
      "contact.rich|接触丰富|接触.*丰富"
    ],
    "pos_claims": [
      "显式.*建模.*接触|接触力.*建模|force.*model|顺应性.*控制|impedance"
    ],
    "neg_claims": [
      "contact.rich.*忽略.*接触|接触丰富.*不需要.*力控|contact.*force.*ignored"
    ]
  },
  "CLF 收敛驱动目标": {
    "terms": [
      "CLF|Control Lyapunov|控制李雅普诺夫"
    ],
    "pos_claims": [
      "CLF.*收敛.*平衡|CLF.*驱动.*收敛|CLF.*渐近稳定|Control Lyapunov.*stabiliz"
    ],
    "neg_claims": [
      "CLF 用于安全边界|CLF 就是 CBF|CLF 等同于 CBF|CLF.*safety barrier function"
    ]
  },
  "CBF vs CLF 功能区别": {
    "terms": [
      "CBF|CBF.*CLF|CLF.*CBF"
    ],
    "pos_claims": [
      "CBF.*安全.*CLF.*收敛|安全集.*CBF.*稳定性.*CLF|CBF.*维持.*CLF.*驱动"
    ],
    "neg_claims": [
      "CBF.*CLF.*功能相同|CBF.*与.*CLF.*等价|CBF.*替代.*CLF"
    ]
  },
  "VLA 输出空间": {
    "terms": [
      "VLA|Vision.Language.Action"
    ],
    "pos_claims": [
      "末端执行器.*位姿|end.effector.*pose|EE.*pose|目标位姿.*输出"
    ],
    "neg_claims": [
      "VLA.*直接.*关节.*力矩|VLA.*joint.*torque.*direct|VLA.*关节级.*指令"
    ]
  },
  "双臂内力协调": {
    "terms": [
      "双臂|bimanual|dual.arm"
    ],
    "pos_claims": [
      "协调规划|内力.*避免|avoid.*internal.*force|closed.loop.*coordination|协调.*内力"
    ],
    "neg_claims": [
      "双臂.*各自.*独立.*规划|bimanual.*no.*coordination|双臂.*内力.*无需处理"
    ]
  },
  "Isaac Lab GPU 并行规模": {
    "terms": [
      "Isaac Lab|IsaacLab|isaac.*lab"
    ],
    "pos_claims": [
      "GPU.*并行|并行.*环境|数千.*环境|thousands.*enviro|massive.*parallel"
    ],
    "neg_claims": [
      "Isaac Lab.*不.*并行|Isaac Lab.*单环境|IsaacLab.*no.*GPU"
    ]
  },
  "Domain Randomization 随机扰动方式": {
    "terms": [
      "domain.randomization|域随机|DR.*参数|随机化.*参数"
    ],
    "pos_claims": [
      "随机.*扰动|随机化.*参数|参数.*分布|parameter.*distribution|uniform.*range"
    ],
    "neg_claims": [
      "DR.*固定.*参数|domain.*random.*fixed.*param|随机化.*无效"
    ]
  },
  "Diffusion Policy 多模态能力": {
    "terms": [
      "diffusion.policy|扩散策略"
    ],
    "pos_claims": [
      "多模态|multimodal|复杂.*操作|multi.modal.*action|多峰.*分布"
    ],
    "neg_claims": [
      "diffusion.*单模态|diffusion.*unimodal|扩散.*单峰.*分布"
    ]
  },
  "VLA 高延迟异步执行": {
    "terms": [
      "VLA|Vision.Language.Action"
    ],
    "pos_claims": [
      "100ms|异步.*执行|async.*execution|action.*chunk|动作.*块.*缓冲"
    ],
    "neg_claims": [
      "VLA.*无需异步|VLA.*同步.*控制|VLA.*低延迟.*同步"
    ]
  },
  "接触丰富顺应性控制": {
    "terms": [
      "contact.rich|接触丰富",
      "force.*control|impedance|力控|阻抗"
    ],
    "pos_claims": [
      "力控|阻抗控制|impedance.*control|force.*control|顺应性.*控制|compliance"
    ],
    "neg_claims": [
      "contact.rich.*纯位置控制|接触丰富.*位置控制.*足够|contact.*pure.*position.*control"
    ]
  },
  "Impedance Control 模型": {
    "terms": [
      "impedance.*control|阻抗控制"
    ],
    "pos_claims": [
      "质量.*弹簧.*阻尼|mass.*spring.*damper|M_d.*B_d.*K_d|虚拟.*物理系统"
    ],
    "neg_claims": [
      "阻抗控制.*无阻尼|阻抗控制.*纯刚性|阻抗控制.*等同PID"
    ]
  },
  "Impedance vs Admittance": {
    "terms": [
      "impedance|阻抗",
      "admittance|导纳"
    ],
    "pos_claims": [
      "阻抗.*位移.*力|导纳.*力.*位移|输入.*误差.*输出.*力矩"
    ],
    "neg_claims": [
      "阻抗.*导纳.*相同|阻抗控制.*输入力|导纳控制.*输出力"
    ]
  },
  "Impedance 柔顺性": {
    "terms": [
      "impedance.*control|阻抗控制"
    ],
    "pos_claims": [
      "主动柔顺|active.*compliance|接触力.*安全|退让"
    ],
    "neg_claims": [
      "阻抗控制.*位置.*绝对|阻抗控制.*不具备柔顺|缺乏柔顺"
    ]
  },
  "Impedance 阻尼调参": {
    "terms": [
      "impedance.*control|阻抗控制",
      "阻尼|damper|B_d"
    ],
    "pos_claims": [
      "临界阻尼|critical.*damping|防止.*震荡|往复振荡"
    ],
    "neg_claims": [
      "阻尼.*越大越好|阻尼.*无需调整|阻尼.*导致.*震荡"
    ]
  },
  "Trajectory Optimization 离线": {
    "terms": [
      "trajectory.*optimization|轨迹优化"
    ],
    "pos_claims": [
      "离线规划|offline|长时域|开环|非线性规划|NLP"
    ],
    "neg_claims": [
      "轨迹优化.*必须在线|轨迹优化.*等于.*MPC|完全实时"
    ]
  },
  "Direct Collocation 约束": {
    "terms": [
      "direct.*collocation|直接配点"
    ],
    "pos_claims": [
      "状态.*控制.*同时优化|动力学.*等式约束|隐式.*接触"
    ],
    "neg_claims": [
      "只优化控制|只优化状态|无动力学约束"
    ]
  },
  "ANYmal SEA": {
    "terms": [
      "ANYmal|anymal"
    ],
    "pos_claims": [
      "串联弹性执行器|SEA|力控执行器|碰撞缓冲"
    ],
    "neg_claims": [
      "ANYmal.*纯刚性电机|ANYmal.*准直接驱动|ANYmal.*QDD"
    ]
  },
  "ANYmal 鲁棒性": {
    "terms": [
      "ANYmal|anymal"
    ],
    "pos_claims": [
      "防水防尘|IP67|工业环境|极端.*地形|RMA|ANYmal.*C"
    ],
    "neg_claims": [
      "ANYmal.*仅限室内|ANYmal.*实验室.*环境|ANYmal.*无感知"
    ]
  },
  "WBC 权重分配": {
    "terms": [
      "WBC|whole.body.control"
    ],
    "pos_claims": [
      "躯干姿态.*高优先级|相对比例|支撑足.*硬约束|Orientation.*Support"
    ],
    "neg_claims": [
      "WBC.*所有任务.*等权|躯干姿态.*低优先级|权重.*绝对值"
    ]
  },
  "WBC 约束松弛": {
    "terms": [
      "WBC|whole.body.control",
      "约束|constraint"
    ],
    "pos_claims": [
      "松弛变量|slack.*variable|惩罚项|软约束"
    ],
    "neg_claims": [
      "WBC.*必须硬约束|WBC.*不可松弛|松弛变量.*无用"
    ]
  },
  "WBC 力矩正则化": {
    "terms": [
      "WBC|whole.body.control",
      "正则|regularization"
    ],
    "pos_claims": [
      "惩罚.*力矩|稳定.*数值|Hessian.*正定|阻尼项"
    ],
    "neg_claims": [
      "WBC.*无需正则化|力矩正则化.*有害|雅可比.*永远满秩"
    ]
  },
  "Boston Dynamics 控制": {
    "terms": [
      "boston.*dynamics|波士顿动力|Atlas"
    ],
    "pos_claims": [
      "基于优化|optimization.*based|WBC.*MPC|全身控制"
    ],
    "neg_claims": [
      "纯.*强化学习|完全弃用.*控制|波士顿动力.*只用.*RL"
    ]
  },
  "Boston Dynamics 硬件": {
    "terms": [
      "boston.*dynamics|波士顿动力|Atlas"
    ],
    "pos_claims": [
      "高功率密度|液压.*全电|定制电机"
    ],
    "neg_claims": [
      "Atlas.*一直液压|全电版.*未发布|低成本电机"
    ]
  },
  "Reward Shaping 平滑": {
    "terms": [
      "reward.*shaping|奖励函数",
      "smoothness|平滑|抖动"
    ],
    "pos_claims": [
      "惩罚.*功耗|惩罚.*加速度|action.*rate|防止.*振荡"
    ],
    "neg_claims": [
      "平滑项.*不重要|只需.*正奖励|无需惩罚.*加速度"
    ]
  },
  "Reward Shaping Air Time": {
    "terms": [
      "air.*time|腾空时间"
    ],
    "pos_claims": [
      "落地后.*结算|诱导.*迈步|产生.*节奏"
    ],
    "neg_claims": [
      "Air Time.*随时给|Air Time.*导致.*站立|不需要.*落地结算"
    ]
  },
  "Locomotion 原地踏步": {
    "terms": [
      "locomotion.*failure|失败模式|原地踏步"
    ],
    "pos_claims": [
      "前进奖励.*低|惩罚.*过重|curriculum|增加.*速度权重"
    ],
    "neg_claims": [
      "原地踏步.*是好现象|无需.*调整奖励|惩罚.*越重越好"
    ]
  },
  "Locomotion 策略崩溃": {
    "terms": [
      "locomotion.*failure|策略崩溃|policy.*collapse"
    ],
    "pos_claims": [
      "学习率.*过大|随机性.*太大|DR.*范围|减小.*学习率"
    ],
    "neg_claims": [
      "策略崩溃.*学习率.*太小|DR.*范围.*必须.*最大|无需.*衰减"
    ]
  },
  "Locomotion 双脚起跳": {
    "terms": [
      "locomotion.*failure|失败模式|双脚起跳|Bunny.*Hop"
    ],
    "pos_claims": [
      "Air Time.*滥用|缺少.*步态约束|限制.*最大值|对角步态"
    ],
    "neg_claims": [
      "双脚起跳.*正常|增加.*Air Time|不需要.*约束"
    ]
  },
  "ZMP 稳定性": {
    "terms": [
      "ZMP|Zero.*Moment.*Point"
    ],
    "pos_claims": [
      "支撑多边形|support.*polygon|落在.*内|不翻倒"
    ],
    "neg_claims": [
      "ZMP.*可以.*外|支撑多边形.*无关|落在边缘.*安全"
    ]
  },
  "CMDP 拉格朗日法": {
    "terms": [
      "CMDP|Constrained.*MDP|Lagrangian|拉格朗日"
    ],
    "pos_claims": [
      "转化为.*惩罚项|交替更新|权重|乘子"
    ],
    "neg_claims": [
      "不使用.*乘子|拉格朗日.*无效|只.*CPO"
    ]
  },
  "VLA Action Tokenization": {
    "terms": [
      "VLA|Vision.Language.Action",
      "分词|tokeniz"
    ],
    "pos_claims": [
      "离散.*Token|映射|Scalar.*Binning|分箱|Codebook|量化"
    ],
    "neg_claims": [
      "VLA.*不使用.*Token|VLA.*纯连续输出|无需量化"
    ]
  },
  "Cross-modal Attention 作用": {
    "terms": [
      "Cross.modal.*Attention|跨模态.*注意力"
    ],
    "pos_claims": [
      "关联|视.*语.*控| RGB.*指令|对齐|拼接到.*序列"
    ],
    "neg_claims": [
      "模态间.*独立|注意力.*无关|无需关注指令"
    ]
  },
  "Allegro Hand 自由度": {
    "terms": [
      "Allegro.*Hand|灵巧手"
    ],
    "pos_claims": [
      "16.*自由度|16.*DOFs|4.*指|4.*fingers"
    ],
    "neg_claims": [
      "Allegro.*拥有.*20.*自由度|Allegro.*具备.*5.*指"
    ]
  },
  "In-hand Reorientation 定义": {
    "terms": [
      "In.hand.*Reorientation|手内重定向"
    ],
    "pos_claims": [
      "不借助于.*外部环境|不利用.*桌面|手指间的协同|改变.*位姿"
    ],
    "neg_claims": [
      "依赖.*桌面|必须放回桌面|非手内"
    ]
  },
  "Preempt_RT 实时性": {
    "terms": [
      "PREEMPT_RT|硬实时"
    ],
    "pos_claims": [
      "补丁|内核源码|SCHED_FIFO|消除.*抖动|消除.*Jitter"
    ],
    "neg_claims": [
      "普通.*Ubuntu.*足够|无需内核补丁|实时性.*无关"
    ]
  },
  "CPU Isolation 效果": {
    "terms": [
      "isolcpus|核心隔离"
    ],
    "pos_claims": [
      "GRUB|预留.*核心|屏蔽.*中断|零中断|独占"
    ],
    "neg_claims": [
      "CPU.*自动平衡|隔离.*无用|无需隔离核心"
    ]
  },
  "LCM 协议特征": {
    "terms": [
      "LCM|UDP.*组播|组播"
    ],
    "pos_claims": [
      "UDP.*组播|Multicast|极低延迟|1000Hz|无.*重传"
    ],
    "neg_claims": [
      "LCM.*基于.*TCP|LCM.*高开销|保证.*重传"
    ]
  },
  "Pinocchio 核心优势": {
    "terms": [
      "Pinocchio|刚体动力学库"
    ],
    "pos_claims": [
      "解析导数|Analytical.*Derivatives|模板元编程|Eigen|Featherstone"
    ],
    "neg_claims": [
      "Pinocchio.*无法.*计算.*导数|Pinocchio.*严重依赖.*动态内存分配"
    ]
  },
  "MuJoCo 接触模型": {
    "terms": [
      "MuJoCo|mjcf"
    ],
    "pos_claims": [
      "凸优化|convex.*optimization|稳定|平滑.*离散化|解析.*求导"
    ],
    "neg_claims": [
      "MuJoCo.*底层.*是.*惩罚冲量|MuJoCo.*接触.*极不稳定|MuJoCo.*不支持.*解析.*求导"
    ]
  },
  "Drake 轨迹优化": {
    "terms": [
      "Drake|Tedrake"
    ],
    "pos_claims": [
      "为优化而生|直接配点|Direct.*Collocation|NLP.*构建|TRI"
    ],
    "neg_claims": [
      "Drake.*仅仿真|Drake.*无优化|不支持.*OCP"
    ]
  },
  "混合中间件架构": {
    "terms": [
      "ROS.*2",
      "LCM"
    ],
    "pos_claims": [
      "分层|ROS.*2.*大脑|LCM.*小脑|ROS.*2.*中高层|LCM.*底层"
    ],
    "neg_claims": [
      "底层.*必须.*ROS.*2|LCM.*负责感知|LCM.*和.*ROS.*2.*竞争"
    ]
  },
  "GelSight 触觉原理": {
    "terms": [
      "GelSight|视觉.*触觉"
    ],
    "pos_claims": [
      "摄像头|硅胶|形变图像|分辨率|千万像素"
    ],
    "neg_claims": [
      "GelSight.*电阻|GelSight.*无摄像头|仅测量压力"
    ]
  },
  "BC Loss 协变量偏移": {
    "terms": [
      "Behavior.*Cloning|BC.*Loss",
      "偏移|shift"
    ],
    "pos_claims": [
      "协变量偏移|Covariate.*Shift|错误累积|Compounding.*Error"
    ],
    "neg_claims": [
      "BC.*无偏移|BC.*绝对鲁棒|数据越多越好"
    ]
  },
  "概率流 ODE 效率": {
    "terms": [
      "概率流",
      "Probability.Flow"
    ],
    "pos_claims": [
      "1-3.*步|加速|确定性|ODE.*求解器|实时性"
    ],
    "neg_claims": [
      "概率流.*慢于.*扩散|概率流.*需要.*100.*步"
    ]
  },
  "流匹配目标函数": {
    "terms": [
      "流匹配|Flow.*Matching"
    ],
    "pos_claims": [
      "回归.*速度场|velocity.*field|最小化.*速度.*差异|线性插值"
    ],
    "neg_claims": [
      "流匹配.*最小化.*Q值|流匹配.*是.*分类任务"
    ]
  },
  "潜空间想象优势": {
    "terms": [
      "潜空间想象|Latent.*Imagination|Dreamer"
    ],
    "pos_claims": [
      "无需.*真实.*交互|快.*100-1000.*倍|过滤.*背景.*噪声|脑海.*预演"
    ],
    "neg_claims": [
      "想象.*必须.*真实采样|潜空间.*比.*物理仿真.*慢"
    ]
  },
  "RSSM 构成": {
    "terms": [
      "RSSM|Recurrent.*State.*Space.*Model"
    ],
    "pos_claims": [
      "Transition|Observation|Reward|确定性.*随机.*状态"
    ],
    "neg_claims": [
      "RSSM.*无随机项|RSSM.*仅包含.*卷积"
    ]
  },
  "生成式世界模型定义": {
    "terms": [
      "生成式世界模型|Generative.*World.*Models"
    ],
    "pos_claims": [
      "以生成代替计算|海量视频数据|模拟.*运动规律|反事实推演"
    ],
    "neg_claims": [
      "底层.*基于.*力学方程|必须.*解析.*计算.*接触力"
    ]
  },
  "Video-as-Simulation 差异": {
    "terms": [
      "Video.as.Simulation"
    ],
    "pos_claims": [
      "算像素|Next-frame.*Prediction|无鸿沟|无需.*手工.*建模"
    ],
    "neg_claims": [
      "必须.*建模.*几何体|Video.as.Simulation.*计算.*冲量"
    ]
  },
  "电池压降风险": {
    "terms": [
      "电池.*压降|Voltage.*Sag"
    ],
    "pos_claims": [
      "瞬时.*掉电|主板.*重启|欠压|独立.*供电"
    ],
    "neg_claims": [
      "压降.*无影响|电池.*电压.*恒定"
    ]
  },
  "关节过热对策": {
    "terms": [
      "关节.*过热|散热|Thermal"
    ],
    "pos_claims": [
      "能效项|主动散热|导热硅脂|减少.*对抗.*出力"
    ],
    "neg_claims": [
      "过热.*必须.*停机|散热.*无关.*控制"
    ]
  },
  "野外感知失效": {
    "terms": [
      "野外|草地|户外",
      "感知|LiDAR|相机"
    ],
    "pos_claims": [
      "过曝|镜面反射|点云.*嘈杂|强度过滤"
    ],
    "neg_claims": [
      "户外.*感知.*更准|感知.*无需.*增强"
    ]
  },
  "地面硬度不匹配": {
    "terms": [
      "地面硬度|草地|刚性地面"
    ],
    "pos_claims": [
      "阻尼.*弹性|深陷泥潭|降低.*Kp|刚度随机化"
    ],
    "neg_claims": [
      "草地.*等同.*硬地|Kp.*越高越好"
    ]
  },
  "SE(3) 6D 表示优点": {
    "terms": [
      "6D.*连续表示|6D.*Rep"
    ],
    "pos_claims": [
      "姿态空间连续|适合.*回归|平滑.*梯度"
    ],
    "neg_claims": [
      "6D.*表示.*不连续|不如.*欧拉角"
    ]
  },
  "Oculus Quest 遥操作": {
    "terms": [
      "Quest|VR.*遥操作"
    ],
    "pos_claims": [
      "低成本|Inside-out.*Tracking|沉浸式|6D.*位姿"
    ],
    "neg_claims": [
      "Quest.*极其昂贵|Quest.*不支持.*手部追踪"
    ]
  },
  "Omniverse 核心底座": {
    "terms": [
      "Omniverse|USD"
    ],
    "pos_claims": [
      "实时协作|数字化孪生|OpenUSD|高保真.*渲染"
    ],
    "neg_claims": [
      "Omniverse.*仅限游戏|Omniverse.*不支持.*物理"
    ]
  },
  "生成式数据增强重点": {
    "terms": [
      "生成式数据增强|Generative.*Data.*Augmentation"
    ],
    "pos_claims": [
      "长尾合成|物体变幻|场景编辑|解决.*瓶颈"
    ],
    "neg_claims": [
      "仅限.*裁剪翻转|增强.*无效"
    ]
  },
  "ELBO 目标": {
    "terms": [
      "ELBO|证据下界|变分"
    ],
    "pos_claims": [
      "重建项|正则项|最小化.*KL散度|一致性"
    ],
    "neg_claims": [
      "ELBO.*最大化.*误差|ELBO.*不含.*KL"
    ]
  },
  "开源人形硬件方案": {
    "terms": [
      "Berkeley.*Humanoid|Roboto.*Origin|ODRI"
    ],
    "pos_claims": [
      "低成本|验证.*算法|QDD.*电机|12-14.*自由度"
    ],
    "neg_claims": [
      "开源硬件.*昂贵|仅限.*工业.*应用"
    ]
  },
  "WBC 奇异点保护": {
    "terms": [
      "奇异点|Singularity"
    ],
    "pos_claims": [
      "膝关节.*伸直|虚拟弹簧力|雅可比.*退化|力矩.*爆炸"
    ],
    "neg_claims": [
      "奇异点.*无需保护|奇异点.*力矩.*最小"
    ]
  },
  "具身数据清洗": {
    "terms": [
      "数据清洗|Data.*Cleaning"
    ],
    "pos_claims": [
      "时序对齐|剔除.*无效动作|修复.*重定向误差|动作分段"
    ],
    "neg_claims": [
      "原始数据.*完美|无需清洗"
    ]
  },
  "CLF vs CBF 目标区别": {
    "terms": [
      "CLF",
      "CBF"
    ],
    "pos_claims": [
      "CLF.*负责稳定性",
      "CBF.*负责安全性",
      "CLF.*旨在.*目标状态",
      "CBF.*旨在.*安全集"
    ],
    "neg_claims": [
      "CLF.*旨在.*安全性",
      "CBF.*旨在.*稳定性",
      "两者.*逻辑完全相同"
    ]
  },
  "数据手套 vs 视觉遥控": {
    "terms": [
      "数据手套|Data.*Glove",
      "视觉.*遥操作|Vision.*Teleop"
    ],
    "pos_claims": [
      "手套.*免疫遮挡",
      "视觉.*低成本",
      "手套.*稳定",
      "视觉.*自然"
    ],
    "neg_claims": [
      "视觉.*免疫遮挡",
      "手套.*低成本",
      "两者.*精度相同"
    ]
  },
  "InEKF 适用层级": {
    "terms": [
      "InEKF",
      "Invariant.*EKF"
    ],
    "pos_claims": [
      "InEKF.*(底层|1kHz|1000Hz|脊髓级)"
    ],
    "neg_claims": [
      "InEKF.*(大脑级|30Hz|高延迟)"
    ]
  },
  "优化派估计优势": {
    "terms": [
      "滑窗优化|Factor.*Graph|因子图"
    ],
    "pos_claims": [
      "非线性拟合.*准|纠正.*漂移|闭环检测|Loop.*Closure|异步.*传感器"
    ],
    "neg_claims": [
      "优化.*不如.*EKF.*准|优化.*无法处理.*非线性"
    ]
  },
  "Model-Free 样本要求": {
    "terms": [
      "Model-Free",
      "无模型"
    ],
    "pos_claims": [
      "样本效率.*低|需.*大量交互|依赖.*仿真训练|数百M步"
    ],
    "neg_claims": [
      "Model-Free.*样本效率.*高|无需.*大规模.*仿真"
    ]
  },
  "Model-Based 规划能力": {
    "terms": [
      "Model-Based",
      "有模型"
    ],
    "pos_claims": [
      "推理未来|具备规划能力|虚拟.*rollout|样本效率.*高"
    ],
    "neg_claims": [
      "Model-Based.*无规划|Model-Based.*样本效率.*低"
    ]
  },
  "Scaling Law 跨形态": {
    "terms": [
      "Scaling.*Law|规模法则",
      "跨形态|不同机器人"
    ],
    "pos_claims": [
      "混合数据.*优于.*单一|多样性.*关键|数据.*多样性|规模.*临界点"
    ],
    "neg_claims": [
      "单一形态.*更佳|多样性.*有害|规模.*无关"
    ]
  },
  "Auto-labeling 技术实现": {
    "terms": [
      "自动化标注|Auto-labeling"
    ],
    "pos_claims": [
      "VLM.*驱动|Teacher-Student|自动.*指令生成|API.*成本低"
    ],
    "neg_claims": [
      "必须.*人工标注|VLM.*无法标注"
    ]
  },
  "Foundation Policy 对齐目标": {
    "terms": [
      "策略对齐|Alignment"
    ],
    "pos_claims": [
      "统一.*隐空间|映射到.*z|跨形态.*迁移|共享表示"
    ],
    "neg_claims": [
      "形态间.*必须独立|无需对齐"
    ]
  },
  "统一 Token 优势": {
    "terms": [
      "统一.*Token|Unified.*Token"
    ],
    "pos_claims": [
      "摒弃.*专用分支|通用.*Transformer|灵活性|自回归"
    ],
    "neg_claims": [
      "必须.*专用分支|Transformer.*不适合多模态"
    ]
  },
  "EtherCAT DC 同步": {
    "terms": [
      "分布式时钟|DC",
      "EtherCAT"
    ],
    "pos_claims": [
      "时钟对齐|对齐.*从站|消除.*抖动|Sync0"
    ],
    "neg_claims": [
      "DC.*增加抖动|DC.*无关紧要"
    ]
  },
  "HAL 设计职责": {
    "terms": [
      "硬件抽象层|HAL"
    ],
    "pos_claims": [
      "屏蔽.*总线差异|解耦|统一接口|逻辑.*API"
    ],
    "neg_claims": [
      "HAL.*必须绑定.*CAN|HAL.*增加.*耦合"
    ]
  },
  "运控对 CPU 要求": {
    "terms": [
      "主控|大脑",
      "CPU|GPU",
      "运控"
    ],
    "pos_claims": [
      "单核主频.*关键|依赖.*单核|QR分解.*难并行|主频.*重要"
    ],
    "neg_claims": [
      "运控.*主要靠.*GPU|单核性能.*不重要"
    ]
  },
  "生成式增强路径": {
    "terms": [
      "生成式数据增强|Generative.*Data.*Augmentation"
    ],
    "pos_claims": [
      "场景编辑|语义编辑|长尾合成|物体变幻|多样化"
    ],
    "neg_claims": [
      "仅限.*旋转裁剪|增强.*无语义"
    ]
  },
  "6D 姿态表示优点": {
    "terms": [
      "6D.*表示|6D.*Rep"
    ],
    "pos_claims": [
      "连续性|姿态空间连续|适合神经网络回归|梯度平滑"
    ],
    "neg_claims": [
      "6D.*表示.*不连续|不如.*四元数.*平滑"
    ]
  },
  "MuJoCo 选型理由": {
    "terms": [
      "MuJoCo|mjcf"
    ],
    "pos_claims": [
      "基于模型.*控制|Model.based.*Control|推导动力学|MPC|iLQR|轨迹优化"
    ],
    "neg_claims": [
      "MuJoCo.*只适合.*Model.free|MuJoCo.*不支持.*MPC"
    ]
  },
  "Isaac Sim 选型理由": {
    "terms": [
      "Isaac.*Sim|Isaac.*Gym"
    ],
    "pos_claims": [
      "千万级并行|千万.*机器人|GPU.*采样|经验采样速度|光线追踪|RTX"
    ],
    "neg_claims": [
      "Isaac.*Sim.*采样慢|Isaac.*Sim.*仅限 CPU|Isaac.*Sim.*无渲染"
    ]
  },
  "Single Shooting 缺点": {
    "terms": [
      "Single.*Shooting|单重打靶"
    ],
    "pos_claims": [
      "高度非线性|容易陷入.*局部最优|蝴蝶效应|难以处理.*中间.*状态.*约束"
    ],
    "neg_claims": [
      "单重打靶.*处理约束.*极佳|单重打靶.*是线性系统"
    ]
  },
  "Direct Collocation 优点": {
    "terms": [
      "Direct.*Collocation|直接配点"
    ],
    "pos_claims": [
      "处理.*极多.*状态约束|初始猜测.*物理不可行.*依然收敛|隐式.*动力学"
    ],
    "neg_claims": [
      "直接配点.*无法处理约束|初始猜测.*必须.*可行"
    ]
  },
  "Contact-Implicit 核心": {
    "terms": [
      "Contact.Implicit|接触隐式"
    ],
    "pos_claims": [
      "互补.*约束|complementarity|无需.*手工.*编排.*时序|自主发现.*步态"
    ],
    "neg_claims": [
      "接触隐式.*需要.*预设.*时序|手动编排.*落地"
    ]
  },
  "VLA 真机分层": {
    "terms": [
      "VLA|Vision.Language.Action",
      "真机|部署"
    ],
    "pos_claims": [
      "中高层策略|不要直接.*驱动.*执行器|低频.*高频.*分层|action.*chunk"
    ],
    "neg_claims": [
      "VLA.*直接.*1kHz.*闭环|VLA.*控制.*脊髓"
    ]
  },
  "SCHED_FIFO 风险": {
    "terms": [
      "SCHED_FIFO|实时线程"
    ],
    "pos_claims": [
      "死循环.*卡死|忘记.*sleep|优先级|拔电源"
    ],
    "neg_claims": [
      "SCHED_FIFO.*绝对安全|系统.*自动.*恢复"
    ]
  },
  "CPU Isolation 配置": {
    "terms": [
      "isolcpus|nohz_full"
    ],
    "pos_claims": [
      "GRUB|屏蔽.*tick|RCU.*回调|屏蔽.*中断"
    ],
    "neg_claims": [
      "isolcpus.*无法屏蔽中断|isolcpus.*内核级.*无关"
    ]
  },
  "RT-1 动作分词": {
    "terms": [
      "RT-1|Action.*Tokenization"
    ],
    "pos_claims": [
      "标量分箱|Scalar.*Binning|256.*bin|独立量化"
    ],
    "neg_claims": [
      "RT-1.*连续回归|RT-1.*不分词"
    ]
  },
  "In-hand Reorientation 挑战": {
    "terms": [
      "In.hand.*Reorientation|手内重定向"
    ],
    "pos_claims": [
      "频繁.*接触切换|感知遮挡|滑移|Slip|离散非线性"
    ],
    "neg_claims": [
      "重定向.*无遮挡|接触.*恒定|重定向.*是线性系统"
    ]
  },
  "π₀ 核心技术": {
    "terms": [
      "π₀|Pi-zero"
    ],
    "pos_claims": [
      "流匹配|Flow.*Matching|Scaling.*Law|规模法则|后训练"
    ],
    "neg_claims": [
      "π₀.*基于.*DQN|π₀.*无预训练"
    ]
  },
  "Allegro Hand 优势": {
    "terms": [
      "Allegro.*Hand|灵巧手"
    ],
    "pos_claims": [
      "结构精简|4指|易于集成触觉|HandLib|DexDex"
    ],
    "neg_claims": [
      "Allegro.*太复杂|Allegro.*无法加触觉"
    ]
  },
  "Embodied Data Cleaning 重点": {
    "terms": [
      "Data.*Cleaning|数据清洗"
    ],
    "pos_claims": [
      "时序对齐|剔除.*异常|重定向误差|插值|重新采样"
    ],
    "neg_claims": [
      "数据.*无需清洗|脏数据.*直接训练"
    ]
  },
  "Actuator Network 作用": {
    "terms": [
      "Actuator.*Network|执行器网络"
    ],
    "pos_claims": [
      "拟合.*真实电机|非线性特性|反向电动势|摩擦|延迟特性|TorchScript"
    ],
    "neg_claims": [
      "执行器网络.*拟合传感器|执行器网络.*代替策略"
    ]
  }
}